{
  "project_info": {
    "project_number": "1006052360183",
    "project_id": "smartwallet-fee35",
    "storage_bucket": "smartwallet-fee35.appspot.com"
  },
  "client": [
    {
      "client_info": {
        "mobilesdk_app_id": "1:1006052360183:android:6317911ce77e666441b8f2",
        "android_client_info": {
          "package_name": "com.infnet.smartwallet"
        }
      },
      "oauth_client": [
        {
          "client_id": "1006052360183-0i35ts1katiqvmhaidpv6cl9ps127phe.apps.googleusercontent.com",
          "client_type": 3
        }
      ],
      "api_key": [
        {
          "current_key": "AIzaSyCLxXUMT-Hm5N70ZC-FrIpjN507CTrUmDM"
        }
      ],
      "services": {
        "appinvite_service": {
          "other_platform_oauth_client": [
            {
              "client_id": "1006052360183-0i35ts1katiqvmhaidpv6cl9ps127phe.apps.googleusercontent.com",
              "client_type": 3
            }
          ]
        }
      }
    }
  ],
  "configuration_version": "1"
}